sphinxcontrib/websupport/__init__.py
sphinxcontrib/websupport/builder.py
sphinxcontrib/websupport/core.py
sphinxcontrib/websupport/errors.py
sphinxcontrib/websupport/utils.py
sphinxcontrib/websupport/writer.py
sphinxcontrib/websupport/files/ajax-loader.gif
sphinxcontrib/websupport/files/comment-bright.png
sphinxcontrib/websupport/files/comment-close.png
sphinxcontrib/websupport/files/comment.png
sphinxcontrib/websupport/files/down-pressed.png
sphinxcontrib/websupport/files/down.png
sphinxcontrib/websupport/files/up-pressed.png
sphinxcontrib/websupport/files/up.png
sphinxcontrib/websupport/files/websupport.js
sphinxcontrib/websupport/search/__init__.py
sphinxcontrib/websupport/search/nullsearch.py
sphinxcontrib/websupport/search/whooshsearch.py
sphinxcontrib/websupport/search/xapiansearch.py
sphinxcontrib/websupport/storage/__init__.py
sphinxcontrib/websupport/storage/differ.py
sphinxcontrib/websupport/storage/sqlalchemy_db.py
sphinxcontrib/websupport/storage/sqlalchemystorage.py
sphinxcontrib/websupport/templates/searchresults.html
sphinxcontrib_websupport-1.2.7.dist-info/entry_points.txt
sphinxcontrib_websupport-1.2.7.dist-info/LICENSE
sphinxcontrib_websupport-1.2.7.dist-info/WHEEL
sphinxcontrib_websupport-1.2.7.dist-info/METADATA
sphinxcontrib_websupport-1.2.7.dist-info/RECORD
