Metadata-Version: 2.1
Name: sphinxcontrib-websupport
Version: 1.2.7
Summary: sphinxcontrib-websupport provides a Python API to easily integrate Sphinx documentation into your Web application
Author-email: Georg Brandl <georg@python.org>
Requires-Python: >=3.9
Classifier: Development Status :: 5 - Production/Stable
Classifier: Environment :: Console
Classifier: Environment :: Web Environment
Classifier: Intended Audience :: Developers
Classifier: Intended Audience :: Education
Classifier: License :: OSI Approved :: BSD License
Classifier: Operating System :: OS Independent
Classifier: Programming Language :: Python
Classifier: Programming Language :: Python :: 3
Classifier: Programming Language :: Python :: 3 :: Only
Classifier: Programming Language :: Python :: 3.9
Classifier: Programming Language :: Python :: 3.10
Classifier: Programming Language :: Python :: 3.11
Classifier: Programming Language :: Python :: 3.12
Classifier: Programming Language :: Python :: 3.13
Classifier: Framework :: Sphinx
Classifier: Framework :: Sphinx :: Extension
Classifier: Topic :: Documentation
Classifier: Topic :: Documentation :: Sphinx
Classifier: Topic :: Text Processing
Classifier: Topic :: Utilities
Requires-Dist: jinja2
Requires-Dist: Sphinx>=5
Requires-Dist: sphinxcontrib-serializinghtml
Requires-Dist: flake8 ; extra == "lint"
Requires-Dist: mypy ; extra == "lint"
Requires-Dist: docutils-stubs ; extra == "lint"
Requires-Dist: pytest ; extra == "test"
Requires-Dist: sqlalchemy ; extra == "whoosh"
Requires-Dist: whoosh ; extra == "whoosh"
Project-URL: Changelog, https://www.sphinx-doc.org/en/master/changes.html
Project-URL: Code, https://github.com/sphinx-doc/sphinxcontrib-websupport
Project-URL: Download, https://pypi.org/project/sphinxcontrib-websupport/
Project-URL: Homepage, https://www.sphinx-doc.org/
Project-URL: Issue tracker, https://github.com/sphinx-doc/sphinx/issues
Provides-Extra: lint
Provides-Extra: test
Provides-Extra: whoosh
